spectrum2_signald/__init__.py
spectrum2_signald/__main__.py
spectrum2_signald/backend.py
spectrum2_signald/signald.py
spectrum2_signald-0.1.4.dist-info/WHEEL
spectrum2_signald-0.1.4.dist-info/METADATA
spectrum2_signald-0.1.4.dist-info/RECORD
