Metadata-Version: 2.1
Name: spectrum2-signald
Version: 0.1.4
Summary: 
Home-page: https://gitlab.com/nicocool84/spectrum2_signald/
Author: Nicolas Cedilnik
Author-email: nicoco@nicoco.fr
Requires-Python: >=3.7,<4.0
Classifier: Programming Language :: Python :: 3
Classifier: Programming Language :: Python :: 3.7
Classifier: Programming Language :: Python :: 3.8
Classifier: Programming Language :: Python :: 3.9
Requires-Dist: pysignald-async (>=0.1.1,<0.2.0)
Requires-Dist: pyspectrum2 (>=0.2.0,<0.3.0)
